pokemon_world/__init__.py
pokemon_world/app.py
pokemon_world/static/audio/pokemon-theme.mp3
pokemon_world/static/images/myhome.jpg
pokemon_world/static/images/pikachu.jpg
pokemon_world/static/images/pokemon_retro_logo.png
pokemon_world/static/images/sacha.png
pokemon_world/static/scripts/main.js
pokemon_world/static/styles/main.css
pokemon_world/templates/index.html
pokemon_world-2025.1.4.dist-info/LICENSE
pokemon_world-2025.1.4.dist-info/METADATA
pokemon_world-2025.1.4.dist-info/WHEEL
pokemon_world-2025.1.4.dist-info/entry_points.txt
pokemon_world-2025.1.4.dist-info/top_level.txt
pokemon_world-2025.1.4.dist-info/RECORD
