Metadata-Version: 2.2
Name: pokemon-world
Version: 2025.1.4
Summary: Lovely Pokemon! Wonderful Pokemon! Gotta Catch Them All
Author-email: lorenzo del medico <lorenzodelmedico@gmail.com>
Maintainer-email: lorenzo del medico <lorenzodelmedico@gmail.com>
License: MIT License
Project-URL: Documentation, https://github.com/lorenzodelmedico/PokemonWorld/README.md
Project-URL: Repository, https://github.com/lorenzodelmedico/PokemonWorld
Keywords: Pokemon,Pikachu,Sacha,Magicarpe,Leviator,Mew,Salamèche,Lorenzodelmedico
Classifier: Development Status :: 4 - Beta
Classifier: Programming Language :: Python
Classifier: Programming Language :: JavaScript
Requires-Python: >=3.8
License-File: LICENSE
Requires-Dist: flask>2.0
